CHANGES.rst
DESCRIPTION.rst
LICENSE
MANIFEST.in
README.md
setup.py
src/adc/redis/__init__.py
src/adc/redis/class_lister.py
src/adc/redis/core.py
src/adc/redis/filter/__init__.py
src/adc/redis/filter/_redis_filter.py
src/adc/redis/filter/_redis_pubsub_filter.py
src/adc/redis/filter/_redis_transcribe.py
src/adc/redis/reader/__init__.py
src/adc/redis/reader/_redis_audio_listen.py
src/adc/redis/reader/_redis_listener.py
src/adc/redis/reader/_redis_reader.py
src/adc/redis/writer/__init__.py
src/adc/redis/writer/_redis_broadcaster.py
src/adc/redis/writer/_redis_data_broadcast.py
src/adc/redis/writer/_redis_writer.py
src/audio_dataset_converter_redis.egg-info/PKG-INFO
src/audio_dataset_converter_redis.egg-info/SOURCES.txt
src/audio_dataset_converter_redis.egg-info/dependency_links.txt
src/audio_dataset_converter_redis.egg-info/entry_points.txt
src/audio_dataset_converter_redis.egg-info/requires.txt
src/audio_dataset_converter_redis.egg-info/top_level.txt