Metadata-Version: 2.1
Name: audio-dataset-converter-redis
Version: 0.0.2
Summary: Redis integration for the audio-dataset-converter library.
Home-page: https://github.com/waikato-llm/audio-dataset-converter-redis
Author: Peter Reutemann
Author-email: fracpete@waikato.ac.nz
License: MIT License
Classifier: Development Status :: 4 - Beta
Classifier: License :: OSI Approved :: MIT License
Classifier: Topic :: Scientific/Engineering :: Artificial Intelligence
Classifier: Topic :: Multimedia :: Sound/Audio :: Conversion
License-File: LICENSE
